notebook_nanoservice/__init__.py
notebook_nanoservice/nanoservice.py
notebook_nanoservice-0.1.3.dist-info/licenses/LICENSE
notebook_nanoservice-0.1.3.dist-info/METADATA
notebook_nanoservice-0.1.3.dist-info/WHEEL
notebook_nanoservice-0.1.3.dist-info/top_level.txt
notebook_nanoservice-0.1.3.dist-info/RECORD
