Metadata-Version: 2.4
Name: notebook_nanoservice
Version: 0.1.3
Summary: Nanoservices for notebooks
Home-page: https://github.com/microsoft/notebook-nanoservice
Author: Your Name
Author-email: danmar@microsoft@example.com
License-File: LICENSE
Dynamic: author
Dynamic: author-email
Dynamic: description
Dynamic: description-content-type
Dynamic: home-page
Dynamic: license-file
Dynamic: summary
